basyx_registry_client/__init__.py
basyx_registry_client/_version.py
basyx_registry_client/async_client.py
basyx_registry_client/client.py
basyx_registry_client/encoding.py
basyx_registry_client/exceptions.py
basyx_registry_client/http.py
basyx_registry_client/pagination.py
basyx_registry_client/resolver.py
basyx_registry_client/integrations/__init__.py
basyx_registry_client/integrations/basyx_client.py
basyx_registry_client/models/__init__.py
basyx_registry_client/models/descriptors.py
basyx_registry_client/models/endpoints.py
basyx_registry_client/models/service.py
basyx_registry_client-0.1.1.dist-info/METADATA
basyx_registry_client-0.1.1.dist-info/WHEEL
basyx_registry_client-0.1.1.dist-info/licenses/LICENSE
basyx_registry_client-0.1.1.dist-info/RECORD
