Metadata-Version: 2.4
Name: basyx-registry-client
Version: 0.1.1
Summary: Python client library for AAS Registry APIs (IDTA-01002 Part 2, v3.x)
Project-URL: Homepage, https://github.com/hadijannat/basyx-registry-client
Project-URL: Documentation, https://github.com/hadijannat/basyx-registry-client#readme
Project-URL: Repository, https://github.com/hadijannat/basyx-registry-client
Author: hadijannat
License: Apache-2.0
License-File: LICENSE
Classifier: Development Status :: 3 - Alpha
Classifier: Intended Audience :: Developers
Classifier: License :: OSI Approved :: Apache Software License
Classifier: Programming Language :: Python :: 3
Classifier: Programming Language :: Python :: 3.10
Classifier: Programming Language :: Python :: 3.11
Classifier: Programming Language :: Python :: 3.12
Classifier: Typing :: Typed
Requires-Python: >=3.10
Requires-Dist: httpx>=0.25.0
Requires-Dist: pydantic>=2.0
Provides-Extra: basyx
Requires-Dist: basyx-client>=0.1; extra == 'basyx'
Provides-Extra: dev
Requires-Dist: build>=1.0; extra == 'dev'
Requires-Dist: mypy>=1.0; extra == 'dev'
Requires-Dist: pytest-asyncio>=0.21; extra == 'dev'
Requires-Dist: pytest>=7.0; extra == 'dev'
Requires-Dist: respx>=0.20; extra == 'dev'
Requires-Dist: ruff>=0.1; extra == 'dev'
Requires-Dist: twine>=5.0; extra == 'dev'
